<?xml version="1.0" encoding="UTF-8"?>
<c xmlns:_="urn:pez"
   xmlns="http://ead3.archivists.org/schema/"
   xmlns:ead="http://ead3.archivists.org/schema/"
   xmlns:tei="http://www.tei-c.org/ns/1.0"
   xmlns:saxon="http://saxon.sf.net/"
   level="item"
   id="i618">
   <did>
      <repository>
         <corpname>
            <part>Benediktinerstift Melk</part>
            <part>Stiftsarchiv</part>
         </corpname>
      </repository>
      <unittitle>Bio-bibliographische Notizen zu Autoren der Melker Reform</unittitle>
      <unitdate/>
      <didnote localtype="datenote">Undatiert.</didnote>
      <dao daotype="derived" coverage="whole" label="TEI Manuskriptbeschreibung" href="msDesc/428880.xml"/>
      <daoset>
         <dao daotype="derived" coverage="whole" label="1r" href="618/428880.tif"/>
         <dao daotype="derived" coverage="whole" label="1v" href="618/428881.tif"/>
         <dao daotype="derived" coverage="whole" label="2r" href="618/428882.tif"/>
         <dao daotype="derived" coverage="whole" label="2v" href="618/428883.tif"/>
         <dao daotype="derived" coverage="whole" label="3r" href="618/428884.tif"/>
         <dao daotype="derived" coverage="whole" label="3v" href="618/428885.tif"/>
         <dao daotype="derived" coverage="whole" label="4r" href="618/428886.tif"/>
         <dao daotype="derived" coverage="whole" label="4v" href="618/428887.tif"/>
      </daoset>
   </did>








   <controlaccess>
      <head>Kategorie</head>
      <genreform>
         <part>Notizen, bio-bibliographische</part>
      </genreform>
   </controlaccess>



   <controlaccess>
      <head>Personen</head>  
      <persname relator="behandelte Person">
         <part localtype="name"/>
         <part localtype="vorname">Johannes Gerson</part>
      </persname>
      <persname relator="behandelte Person">
         <part localtype="name"/>
         <part localtype="vorname">Johannes von Weilheim (Schlitpacher)</part>
      </persname>
      <persname relator="behandelte Person">
         <part localtype="name"/>
         <part localtype="vorname">Martin von Senging</part>
      </persname>
      <persname relator="behandelte Person">
         <part localtype="name"/>
         <part localtype="vorname">Christophorus Lieb von Isen</part>
      </persname>
   </controlaccess>
   <controlaccess>
      <head>Regionen</head>
      <geogname>
         <part>Österreich</part>
      </geogname>
   </controlaccess>

   <controlaccess>
      <head>Institutionen</head>
      <corpname>
         <part>geistliche</part>
         <part>Benediktiner</part>
         <part>Österreichische Kongregation</part>
         <part>Melk</part>
      </corpname>
   </controlaccess>


   <scopecontent>
      <head>Beschreibung</head>
      <p>Bio-bibliographische Notizen zu Autoren der Melker Reform, Hand BP?</p>
   </scopecontent>
   <bibliography>
      <head>Literatur</head>
      <p>Zur Melker Reform: Meta NIEDERKORN-BRUCK, Die Melker Reform im Spiegel der Visitationen (Mitteilungen des Instituts für Österreichische Geschichtsforschung Erg.bd. 30, Wien–München 1994); Franz Xaver THOMA, Petrus von Rosenheim O. S. B. Ein Beitrag zur Melker Reformbewegung. Studien und Mitteilungen zur Geschichte des Benediktiner-Ordens und seiner Zweige 45 (1927) 94–222.</p>
   </bibliography>




</c>
