<?xml version="1.0" encoding="UTF-8"?>
<c xmlns:_="urn:pez"
   xmlns="http://ead3.archivists.org/schema/"
   xmlns:ead="http://ead3.archivists.org/schema/"
   xmlns:tei="http://www.tei-c.org/ns/1.0"
   xmlns:saxon="http://saxon.sf.net/"
   level="item"
   id="i791">
   <did>
      <repository>
         <corpname>
            <part>Benediktinerstift Melk</part>
            <part>Stiftsbibliothek</part>
         </corpname>
      </repository>
      <unitid>Cod. 0656_1</unitid>
      <unittitle>Cod. Mell. 656/1: Irimbertus Admontensis 1</unittitle>
      <didnote localtype="datenote">Laut Glassner, Neuzeitliche Handschriften (vgl. Literaturfeld) 1. Drittel 18. Jh.</didnote>
      <dao daotype="derived" coverage="whole" label="TEI Manuskriptbeschreibung" href="msDesc/475730.xml"/>
   </did>








   <controlaccess>
      <head>Kategorie</head>
      <genreform>
         <part>Handschrift</part>
      </genreform>
      <genreform>
         <part>Druckvorlage</part>
      </genreform>
   </controlaccess>



   <controlaccess>
      <head>Personen</head>  
      <persname relator="cre">
         <part localtype="name"/>
         <part localtype="vorname">Irimbert von Admont</part>
      </persname>
      <persname relator="cre">
         <part localtype="name">Pez</part>
         <part localtype="vorname">Bernhard</part>
      </persname>
   </controlaccess>
   <controlaccess>
      <head>Regionen</head>
      <geogname>
         <part>Österreich</part>
      </geogname>
   </controlaccess>

   <controlaccess>
      <head>Institutionen</head>
      <corpname identifier="http://d-nb.info/gnd/126116-2" source="GND">
         <part>geistliche</part>
         <part>Benediktiner</part>
         <part>Salzburgische Kongregation</part>
         <part>Admont</part>
         <part localtype="identifier">http://d-nb.info/gnd/126116-2</part>
         <part localtype="identifier">http://viaf.org/viaf/133125683</part>
         <part localtype="identifier">http://www.geonames.org/2782979/admont.html</part>
      </corpname>
      <corpname identifier="http://d-nb.info/gnd/82463-X" source="GND">
         <part>geistliche</part>
         <part>Benediktiner</part>
         <part>Österreichische Kongregation</part>
         <part>Melk</part>
         <part localtype="identifier">http://klosterdatenbank.germania-sacra.de/gsn/3265</part>
         <part localtype="identifier">http://d-nb.info/gnd/82463-X</part>
         <part localtype="identifier">http://viaf.org/viaf/316399876</part>
         <part localtype="identifier">http://www.geonames.org/7536060/kloster-melk.html</part>
      </corpname>
   </controlaccess>


   <scopecontent>
      <head>Beschreibung</head>
      <p>Cod. 656/1 (olim 1627, 1814) besteht aus 15 durchgezählten Sexternionen. Zahlreiche Korrekturen Hand BP. Deutsche Anweisungen für den Drucker. Moderne Tintenfoliierung. 1r–178v: Irimbert von Admont, "Expositio in librum I Regum". Teildruck aus Lib. IV: Pez, BA VIII (1725) 455–464 (mit Praefatio b3v–b4v: Verweis auf die Dissertatio isagogica in Pez, TA II, XI–XVI; kündigt eine vollständige Ausgabe des Kommentars zu den Büchern der Könige an). Für Teildruck der vier Prologe siehe  Braun (vgl. Literaturfeld). Druckvorlage, jedoch Druck nicht zustande gekommen, deutsche Anmerkungen für den Drucker: 1r: "NB Seze disen Titel mit grosser Fractur", 1r rechts oben Titel gestrichen, 1r oberer Freirand Titel von späterer Hand: "Ven. Irimbertus Abb. Admont. in Lib. I. Regum". Die geplante Ausgabe durch BP wäre die Erstausgabe gewesen. Schreiber: Korrekturen Hand BP. Vorlage nicht genannt. Aktueller Bibliotheksort und Signatur: Admont, Cod. 16 (?), vermutlich die einzige Hs.</p>
   </scopecontent>





</c>
