<?xml version="1.0" encoding="UTF-8"?>
<c xmlns:_="urn:pez"
   xmlns="http://ead3.archivists.org/schema/"
   xmlns:ead="http://ead3.archivists.org/schema/"
   xmlns:tei="http://www.tei-c.org/ns/1.0"
   xmlns:saxon="http://saxon.sf.net/"
   level="item"
   id="i812">
   <did>
      <repository>
         <corpname>
            <part>Benediktinerstift Melk</part>
            <part>Stiftsbibliothek</part>
         </corpname>
      </repository>
      <unitid>Cod. 1782</unitid>
      <unittitle>Cod. Mell. 1782: Bernhard Pez, Logicalium conclusionum dilucida epitome</unittitle>
      <didnote localtype="datenote"/>
      <dao daotype="derived" coverage="whole" label="TEI Manuskriptbeschreibung" href="msDesc/486656.xml"/>
   </did>








   <controlaccess>
      <head>Kategorie</head>
      <genreform>
         <part>Handschrift</part>
      </genreform>
   </controlaccess>



   <controlaccess>
      <head>Personen</head>  
      <persname relator="cre">
         <part localtype="name">Pez</part>
         <part localtype="vorname">Bernhard</part>
      </persname>
   </controlaccess>
   <controlaccess>
      <head>Regionen</head>
      <geogname>
         <part>Österreich</part>
      </geogname>
   </controlaccess>

   <controlaccess>
      <head>Institutionen</head>
      <corpname identifier="http://d-nb.info/gnd/82463-X" source="GND">
         <part>geistliche</part>
         <part>Benediktiner</part>
         <part>Österreichische Kongregation</part>
         <part>Melk</part>
         <part localtype="identifier">http://klosterdatenbank.germania-sacra.de/gsn/3265</part>
         <part localtype="identifier">http://d-nb.info/gnd/82463-X</part>
         <part localtype="identifier">http://viaf.org/viaf/316399876</part>
         <part localtype="identifier">http://www.geonames.org/7536060/kloster-melk.html</part>
      </corpname>
   </controlaccess>


   <scopecontent>
      <head>Beschreibung</head>
      <p>Cod. 1782 (olim 1836, 1729) besteht aus einem Faszikel, moderne Tintenfoliierung. 1r–35v: BP, "Logicalium conclusionum dilucida epitome", Ir–IIv, 36r–43v leer, IIIr: Titelblatt. Mitschrift der Logikvorlesung am Melker Hausstudium. IIIr: Nach dem Titel Verfasser und Datierung: "Collecta a F. Bernardo Pez eiusdem Facultatis pro tunc auditore anno 1701".</p>
   </scopecontent>





</c>
