<?xml version="1.0" encoding="UTF-8"?>
<c xmlns:_="urn:pez"
   xmlns="http://ead3.archivists.org/schema/"
   xmlns:ead="http://ead3.archivists.org/schema/"
   xmlns:tei="http://www.tei-c.org/ns/1.0"
   xmlns:saxon="http://saxon.sf.net/"
   level="item"
   id="i375">
   <did>
      <repository>
         <corpname>
            <part>Benediktinerstift Melk</part>
            <part>Stiftsarchiv</part>
         </corpname>
      </repository>
      <unittitle>Briefauszüge: Sancto Felice an BP</unittitle>
      <unitdate>19. Jh.</unitdate>
      <didnote localtype="datenote">Im Zusammenhang mit der Pez-Forschung im 19. Jahrhundert.</didnote>
      <dao daotype="derived" coverage="whole" label="TEI Manuskriptbeschreibung" href="msDesc/419911.xml"/>
      <daoset>
         <dao daotype="derived" coverage="whole" label="1r" href="375/419911.tif"/>
         <dao daotype="derived" coverage="whole" label="1v" href="375/419912.tif"/>
         <dao daotype="derived" coverage="whole" label="2r" href="375/419913.tif"/>
         <dao daotype="derived" coverage="whole" label="2v" href="375/419914.tif"/>
      </daoset>
   </did>








   <controlaccess>
      <head>Kategorie</head>
      <genreform>
         <part>Briefauszug</part>
      </genreform>
   </controlaccess>



   <controlaccess>
      <head>Personen</head>  
      <persname relator="Urheber">
         <part localtype="name">Mayer</part>
         <part localtype="vorname">Theodor</part>
      </persname>
      <persname relator="Urheber">
         <part localtype="name">Sancto Felice</part>
         <part localtype="vorname">Johann a</part>
      </persname>
      <persname relator="behandelte Person">
         <part localtype="name">Pez</part>
         <part localtype="vorname">Bernhard</part>
      </persname>
   </controlaccess>
   <controlaccess>
      <head>Regionen</head>
      <geogname>
         <part>Österreich</part>
      </geogname>
   </controlaccess>

   <controlaccess>
      <head>Institutionen</head>
      <corpname>
         <part>geistliche</part>
         <part>Benediktiner</part>
         <part>Österreichische Kongregation</part>
         <part>Melk</part>
      </corpname>
      <corpname>
         <part>geistliche</part>
         <part>Trinitarier</part>
         <part>Wien</part>
      </corpname>
   </controlaccess>

   <relatedmaterial>
      <head>Pez-Briefe im direkten Zusammenhang mit dem Stück</head>
      <p>Sancto Felice an BP: 1714-10-14, 1715-07-24, 1715-08-24. Sancto Felice an NN: 1716-03-02.</p>
   </relatedmaterial>
   <scopecontent>
      <head>Beschreibung</head>
      <p>Auszüge aus den Briefen Sancto Felice an BP, Hand Mayer. Datierungen teilweise irrig.</p>
   </scopecontent>
   <bibliography>
      <head>Literatur</head>
      <p>Zu Mayer: Catalogus religiosorum ordinis S.P. Benedicti in monasterio Mellicensi (Wien 1855). Zu Sancto Felice und Briefen: Christine GLASSNER, Verzeichnis der im Nachlass der Melker Historiker Bernhard und Hieronymus Pez erhaltenen Briefe. SMGB 110 (1999) 195–243; Thomas WALLNIG–Thomas STOCKINGER, Die gelehrte Korrespondenz der Brüder Pez. Text, Regesten, Kommentare, 1: 1709–1715 (QIÖG 2/1, Wien–München 2010).</p>
   </bibliography>




</c>
